WebAssistant/__init__.py
WebAssistant/hub.py
WebAssistant-0.0.4.dist-info/LICENSE
WebAssistant-0.0.4.dist-info/METADATA
WebAssistant-0.0.4.dist-info/WHEEL
WebAssistant-0.0.4.dist-info/top_level.txt
WebAssistant-0.0.4.dist-info/RECORD
