Metadata-Version: 2.1
Name: WebAssistant
Version: 0.0.4
Summary: WebAssistant: Quickly Deploy an AI Assistant Chatbot for your Personal Webpage
Home-page: https://github.com/shreyanmitra/WebAssistant
Author: Shreyan Mitra
Keywords: ai chatbot website-builder gpt-4 rag
License-File: LICENSE
Requires-Dist: gradio
Requires-Dist: langchain-chroma
Requires-Dist: langchain-community
Requires-Dist: langchain-core
Requires-Dist: langchain-text-splitters
Requires-Dist: langchainhub
Requires-Dist: pandas
Requires-Dist: xmltodict
Requires-Dist: urllib3
Requires-Dist: certifi
Requires-Dist: warnings
